tf_summary_reader/__init__.py
tf_summary_reader/collect_tf_event_files.py
tf_summary_reader/filter_out_modified_file.py
tf_summary_reader/get_summary_data.py
tf_summary_reader/main.py
tf_summary_reader/process_record.py
tf_summary_reader/read_summary_as_data_frame.py
tf_summary_reader/read_summary_data_periodically.py
tf_summary_reader/read_summay.py
tf_summary_reader/read_tf_event_file.py
tf_summary_reader/preprocess/__init__.py
tf_summary_reader/preprocess/process_record_clean_empty_summary.py
tf_summary_reader/preprocess/process_record_merge_summary.py
tf_summary_reader-0.2.0.dist-info/AUTHORS.rst
tf_summary_reader-0.2.0.dist-info/LICENSE
tf_summary_reader-0.2.0.dist-info/METADATA
tf_summary_reader-0.2.0.dist-info/WHEEL
tf_summary_reader-0.2.0.dist-info/top_level.txt
tf_summary_reader-0.2.0.dist-info/RECORD
