Metadata-Version: 2.1
Name: tf-summary-reader
Version: 0.2.0
Summary: A package for read data from tensorflow summary files
Home-page: https://github.com/howl-anderson/tf_summary_reader
Author: Xiaoquan Kong
Author-email: u1mail2me@gmail.com
License: MIT license
Keywords: tf_summary_reader
Platform: UNKNOWN
Classifier: Development Status :: 2 - Pre-Alpha
Classifier: Intended Audience :: Developers
Classifier: License :: OSI Approved :: MIT License
Classifier: Natural Language :: English
Classifier: Programming Language :: Python :: 2
Classifier: Programming Language :: Python :: 2.7
Classifier: Programming Language :: Python :: 3
Classifier: Programming Language :: Python :: 3.5
Classifier: Programming Language :: Python :: 3.6
Classifier: Programming Language :: Python :: 3.7
Requires-Python: >=2.7, !=3.0.*, !=3.1.*, !=3.2.*, !=3.3.*, !=3.4.*
Requires-Dist: pandas
Requires-Dist: tensorflow (<2.0.0,>=1.15.0)
